mkdocs_paralex_plugin/__init__.py
mkdocs_paralex_plugin/convert.py
mkdocs_paralex_plugin/paralex.png
mkdocs_paralex_plugin/plugin.py
mkdocs_paralex_plugin/utils.py
mkdocs_paralex_plugin/css/paralex_styles.css
mkdocs_paralex_plugin/templates/paradigm.md
mkdocs_paralex_plugin/templates/table.md
mkdocs_paralex_plugin-0.1.13b0.dist-info/LICENSE
mkdocs_paralex_plugin-0.1.13b0.dist-info/METADATA
mkdocs_paralex_plugin-0.1.13b0.dist-info/WHEEL
mkdocs_paralex_plugin-0.1.13b0.dist-info/entry_points.txt
mkdocs_paralex_plugin-0.1.13b0.dist-info/top_level.txt
mkdocs_paralex_plugin-0.1.13b0.dist-info/RECORD
