Metadata-Version: 2.1
Name: mkdocs-paralex-plugin
Version: 0.1.13b0
Summary: Build static sites for paralex lexicons
Home-page: https://gitlab.com/sbeniamine/paralex-site/
Author: Sacha Beniamine
Keywords: mkdocs
Classifier: Programming Language :: Python :: 3
Classifier: License :: OSI Approved :: GNU General Public License v3 (GPLv3)
Classifier: Operating System :: OS Independent
Requires-Python: >=3.7
License-File: LICENSE
Requires-Dist: mkdocs
Requires-Dist: pandas >=2.2.0
Requires-Dist: frictionless >=5.16.0
Requires-Dist: unidecode
Requires-Dist: tqdm
Requires-Dist: paralex >=1.0.16
Requires-Dist: minify-html
Requires-Dist: pybtex
